Metadata-Version: 1.0
Name: json2pyclass
Version: 1.0.1
Summary: json2pyclass
Home-page: UNKNOWN
Author: Bogdan Mustiata
Author-email: bogdan.mustiata@gmail.com
License: BSD
Platform: UNKNOWN
